redis_admin_client/__init__.py
redis_admin_client/redis_admin_client.py
redis_admin_client-0.1.1.dist-info/WHEEL
redis_admin_client-0.1.1.dist-info/METADATA
redis_admin_client-0.1.1.dist-info/RECORD
