Metadata-Version: 2.1
Name: redis-admin-client
Version: 0.1.1
Summary: High level redis client
Author: Kharthigeyan Satyamurthy
Author-email: kharthigeyan@gmail.com
Requires-Python: >=3.8,<4.0
Classifier: Programming Language :: Python :: 3
Classifier: Programming Language :: Python :: 3.10
Classifier: Programming Language :: Python :: 3.8
Classifier: Programming Language :: Python :: 3.9
Requires-Dist: altair (>=4.2.0,<5.0.0)
Requires-Dist: ipcalc (>=1.99.0,<2.0.0)
Requires-Dist: pandas (>=1.4.3,<2.0.0)
Requires-Dist: pandasql (>=0.7.3,<0.8.0)
Requires-Dist: plotly (>=5.9.0,<6.0.0)
Requires-Dist: plotly-express (>=0.4.1,<0.5.0)
Requires-Dist: ray (>=1.13.0,<2.0.0)
Requires-Dist: redis (>=4.3.4,<5.0.0)
Requires-Dist: requests (>=2.28.1,<3.0.0)
Requires-Dist: seaborn (>=0.11.2,<0.12.0)
